LICENSE
MANIFEST.in
README.md
pyproject.toml
setup.cfg
setup.py
fast_bocpd/__init__.py
fast_bocpd/_bindings.py
fast_bocpd/core.py
fast_bocpd/hazard.py
fast_bocpd/models.py
fast_bocpd/utils.py
fast_bocpd.egg-info/PKG-INFO
fast_bocpd.egg-info/SOURCES.txt
fast_bocpd.egg-info/dependency_links.txt
fast_bocpd.egg-info/not-zip-safe
fast_bocpd.egg-info/requires.txt
fast_bocpd.egg-info/top_level.txt
fast_bocpd/_c/bernoulli_beta.c
fast_bocpd/_c/bernoulli_beta.h
fast_bocpd/_c/binomial_beta.c
fast_bocpd/_c/binomial_beta.h
fast_bocpd/_c/bocpd_core.c
fast_bocpd/_c/bocpd_core.h
fast_bocpd/_c/gamma_gamma_fixed_shape.c
fast_bocpd/_c/gamma_gamma_fixed_shape.h
fast_bocpd/_c/gaussian_nig.c
fast_bocpd/_c/gaussian_nig.h
fast_bocpd/_c/hazard.c
fast_bocpd/_c/hazard.h
fast_bocpd/_c/poisson_gamma.c
fast_bocpd/_c/poisson_gamma.h
fast_bocpd/_c/student_t_ng.c
fast_bocpd/_c/student_t_ng.h
fast_bocpd/_c/student_t_ng_grid.c
fast_bocpd/_c/student_t_ng_grid.h