Metadata-Version: 2.4
Name: fast-bocpd
Version: 1.0.0
Summary: Fast Bayesian Online Changepoint Detection with C backend
Author-email: Tiaan Viviers <tiaanviv@gmail.com>
License: MIT
Project-URL: Homepage, https://github.com/TiaanViviers/Fast_BOCPD
Project-URL: Documentation, https://fast-bocpd.readthedocs.io
Project-URL: Repository, https://github.com/TiaanViviers/Fast_BOCPD
Project-URL: Issues, https://github.com/TiaanViviers/Fast_BOCPD/issues
Keywords: bayesian,changepoint,detection,online,streaming,timeseries,bocpd
Classifier: Development Status :: 5 - Production/Stable
Classifier: Intended Audience :: Science/Research
Classifier: Intended Audience :: Developers
Classifier: Programming Language :: Python :: 3
Classifier: Programming Language :: Python :: 3.9
Classifier: Programming Language :: Python :: 3.10
Classifier: Programming Language :: Python :: 3.11
Classifier: Programming Language :: Python :: 3.12
Classifier: Programming Language :: C
Classifier: Topic :: Scientific/Engineering :: Information Analysis
Classifier: Topic :: Scientific/Engineering :: Mathematics
Classifier: Operating System :: OS Independent
Requires-Python: >=3.9
Requires-Dist: numpy>=1.21.0
